geekmorn_first_package.py
geekmorn_first_package-0.1.0.dist-info/METADATA
geekmorn_first_package-0.1.0.dist-info/WHEEL
geekmorn_first_package-0.1.0.dist-info/RECORD
